dfpercentile/__init__.py
dfpercentile/setup.py
dfpercentile_pkg_chanrl-0.0.1.dist-info/LICENSE
dfpercentile_pkg_chanrl-0.0.1.dist-info/METADATA
dfpercentile_pkg_chanrl-0.0.1.dist-info/WHEEL
dfpercentile_pkg_chanrl-0.0.1.dist-info/top_level.txt
dfpercentile_pkg_chanrl-0.0.1.dist-info/RECORD
