Metadata-Version: 2.1
Name: dfpercentile-pkg-chanrl
Version: 0.0.1
Summary: Package to separate a df by percentile on a column, bootstrap from the upper/lower bounds, create scatter plot and histogram, return p values on ttests and pearsons correlation coefficient
Home-page: https://github.com/chanrl/df-percentile
Author: Richard Chan
Author-email: richard129chan@gmail.com
License: UNKNOWN
Platform: UNKNOWN
Classifier: Programming Language :: Python :: 3
Classifier: License :: OSI Approved :: MIT License
Classifier: Operating System :: OS Independent
Requires-Python: >=3.6
